short_con/__init__.py
short_con/main.py
short_con/version.py
short_con-2.1.0.dist-info/LICENSE
short_con-2.1.0.dist-info/METADATA
short_con-2.1.0.dist-info/WHEEL
short_con-2.1.0.dist-info/top_level.txt
short_con-2.1.0.dist-info/RECORD
