Metadata-Version: 2.1
Name: short-con
Version: 2.1.0
Summary: Constants collections without hassle
Home-page: https://github.com/hindman/short-con
Author: Monty Hindman
Author-email: mhindman@gmail.com
License: MIT
Classifier: Development Status :: 5 - Production/Stable
Classifier: Intended Audience :: Developers
Classifier: License :: OSI Approved :: MIT License
Classifier: Operating System :: OS Independent
Classifier: Programming Language :: Python :: 3
Classifier: Programming Language :: Python :: 3.7
Classifier: Programming Language :: Python :: 3.8
Classifier: Programming Language :: Python :: 3.9
Classifier: Programming Language :: Python :: 3.10
Classifier: Programming Language :: Python :: 3.11
Classifier: Programming Language :: Python :: 3.12
Classifier: Programming Language :: Python :: 3.13
Classifier: Topic :: Software Development
Requires-Python: >=3.7
License-File: LICENSE
Requires-Dist: kwexception
Provides-Extra: dev
Requires-Dist: build ; extra == 'dev'
Requires-Dist: invoke ; extra == 'dev'
Requires-Dist: ipython ; extra == 'dev'
Requires-Dist: pycodestyle ; extra == 'dev'
Requires-Dist: twine ; extra == 'dev'
Requires-Dist: virtualenv ; extra == 'dev'
Requires-Dist: virtualenvwrapper ; extra == 'dev'
Provides-Extra: test
Requires-Dist: pytest ; extra == 'test'
Requires-Dist: pytest-cov ; extra == 'test'
Requires-Dist: tox ; extra == 'test'
